braz/__init__.py
braz/cifrar/__init__.py
braz/cifrar/cesar.py
braz/cifrar/cod_ascii.py
braz/cifrar/morse.py
braz/cifrar/numerico.py
braz/cifrar/vigenere.py
braz/constantes.py
braz/criptografar/__init__.py
braz/criptografar/b16.py
braz/criptografar/b32.py
braz/criptografar/b64.py
braz/decifrar/__init__.py
braz/decifrar/cesar.py
braz/decifrar/cod_ascii.py
braz/decifrar/morse.py
braz/decifrar/numerico.py
braz/decifrar/vigenere.py
braz/descriptografar/__init__.py
braz/descriptografar/b16.py
braz/descriptografar/b32.py
braz/descriptografar/b64.py
braz/gerar/__init__.py
braz/gerar/cnpj.py
braz/gerar/cpf.py
braz/gerar/ie.py
braz/gerar/pis_pasep.py
braz/gerar/renavam.py
braz/gerar/rg.py
braz/gerar/senha.py
braz/gerar/titulo_eleitor.py
braz/manipular/__init__.py
braz/manipular/manipular.py
braz/uteis.py
braz/validar/__init__.py
braz/validar/cnpj.py
braz/validar/cpf.py
braz/validar/ie.py
braz/validar/pis_pasep.py
braz/validar/renavam.py
braz/validar/rg.py
braz/validar/senha.py
braz/validar/titulo_eleitor.py
braz/validar/validar.py
braz-0.1.0.dist-info/WHEEL
braz-0.1.0.dist-info/METADATA
braz-0.1.0.dist-info/RECORD
