Metadata-Version: 2.1
Name: braz
Version: 0.1.0
Summary: 🎲 Gerador, validador, cifras, criptografias e manipulação de strings.
License: MIT
Keywords: braz,gerador,validador,cifra,criptografia,manipulação,string
Author: Miguel Alves Cordeiro Braz
Author-email: dev.macb@gmail.com
Requires-Python: >=3.10,<4.0
Classifier: Framework :: IDLE
Classifier: Framework :: IPython
Classifier: License :: OSI Approved :: MIT License
Classifier: Natural Language :: Portuguese (Brazilian)
Classifier: Programming Language :: Python :: 3
Classifier: Programming Language :: Python :: 3.10
Classifier: Programming Language :: Python :: 3.11
Classifier: Programming Language :: Python :: 3
Classifier: Topic :: Software Development :: Code Generators
Project-URL: Bug Tracker, https://github.com/dev-macb/braz/issues
Project-URL: documentation, https://github.com/dev-macb/braz/
Project-URL: homepage, https://python-poetry.org/
Project-URL: repository, https://github.com/dev-macb/braz
